[
  {
    "total_id": "201901121583061108447532KMuC",
    "vehicle_id": "arts16_1",
    "park_id": "shanghai_disney",
    "total_running_time": "4273",
    "total_running_length": "3432.49357932",
    "total_emergency_stop_counts": "0",
    "total_emergency_stop_duration": "0",
    "total_take_over_counts": "0",
    "total_take_over_duration": "0",
    "total_bag_size": "0",
    "total_fault_counts": "0",
    "total_accident_counts": "0",
    "day": "20190112",
    "create_time": "1583061108"
  },
  {
    "total_id": "201901141583061210553430CsqA",
    "vehicle_id": "arts16_1",
    "park_id": "shanghai_disney",
    "total_running_time": "13255",
    "total_running_length": "11805.5655675",
    "total_emergency_stop_counts": "0",
    "total_emergency_stop_duration": "0",
    "total_take_over_counts": "0",
    "total_take_over_duration": "0",
    "total_bag_size": "0",
    "total_fault_counts": "0",
    "total_accident_counts": "0",
    "day": "20190114",
    "create_time": "1583061211"
  },
  {
    "total_id": "201901161583061296209300yjsZ",
    "vehicle_id": "arts16_1",
    "park_id": "shanghai_disney",
    "total_running_time": "17286",
    "total_running_length": "15716.9808955",
    "total_emergency_stop_counts": "0",
    "total_emergency_stop_duration": "0",
    "total_take_over_counts": "0",
    "total_take_over_duration": "0",
    "total_bag_size": "0",
    "total_fault_counts": "0",
    "total_accident_counts": "0",
    "day": "20190116",
    "create_time": "1583061296"
  },
  {
    "total_id": "201901171583061346463460vOza",
    "vehicle_id": "arts16_1",
    "park_id": "shanghai_disney",
    "total_running_time": "20934",
    "total_running_length": "18322.3855914",
    "total_emergency_stop_counts": "0",
    "total_emergency_stop_duration": "0",
    "total_take_over_counts": "0",
    "total_take_over_duration": "0",
    "total_bag_size": "0",
    "total_fault_counts": "0",
    "total_accident_counts": "0",
    "day": "20190117",
    "create_time": "1583061347"
  },
  {
    "total_id": "201901181583061400702570bvdn",
    "vehicle_id": "arts16_1",
    "park_id": "shanghai_disney",
    "total_running_time": "28286",
    "total_running_length": "23707.7650171",
    "total_emergency_stop_counts": "0",
    "total_emergency_stop_duration": "0",
    "total_take_over_counts": "0",
    "total_take_over_duration": "0",
    "total_bag_size": "0",
    "total_fault_counts": "0",
    "total_accident_counts": "0",
    "day": "20190118",
    "create_time": "1583061401"
  },
  {
    "total_id": "201901191583061452061920whbJ",
    "vehicle_id": "arts16_1",
    "park_id": "shanghai_disney",
    "total_running_time": "32935",
    "total_running_length": "27689.8066199",
    "total_emergency_stop_counts": "0",
    "total_emergency_stop_duration": "0",
    "total_take_over_counts": "0",
    "total_take_over_duration": "0",
    "total_bag_size": "0",
    "total_fault_counts": "0",
    "total_accident_counts": "0",
    "day": "20190119",
    "create_time": "1583061452"
  },
  {
    "total_id": "201901201583061504942523OqZw",
    "vehicle_id": "arts16_1",
    "park_id": "shanghai_disney",
    "total_running_time": "39769",
    "total_running_length": "31186.316907",
    "total_emergency_stop_counts": "0",
    "total_emergency_stop_duration": "0",
    "total_take_over_counts": "0",
    "total_take_over_duration": "0",
    "total_bag_size": "0",
    "total_fault_counts": "0",
    "total_accident_counts": "0",
    "day": "20190120",
    "create_time": "1583061505"
  },
  {
    "total_id": "201901211583061559565535afZy",
    "vehicle_id": "arts16_1",
    "park_id": "shanghai_disney",
    "total_running_time": "44534",
    "total_running_length": "35120.3737858",
    "total_emergency_stop_counts": "0",
    "total_emergency_stop_duration": "0",
    "total_take_over_counts": "0",
    "total_take_over_duration": "0",
    "total_bag_size": "0",
    "total_fault_counts": "0",
    "total_accident_counts": "0",
    "day": "20190121",
    "create_time": "1583061560"
  },
  {
    "total_id": "201901221583061618689430GJpr",
    "vehicle_id": "arts16_1",
    "park_id": "shanghai_disney",
    "total_running_time": "50835",
    "total_running_length": "39033.8607469",
    "total_emergency_stop_counts": "0",
    "total_emergency_stop_duration": "0",
    "total_take_over_counts": "0",
    "total_take_over_duration": "0",
    "total_bag_size": "0",
    "total_fault_counts": "0",
    "total_accident_counts": "0",
    "day": "20190122",
    "create_time": "1583061619"
  },
  {
    "total_id": "201901231583061677679657mduM",
    "vehicle_id": "arts16_1",
    "park_id": "shanghai_disney",
    "total_running_time": "55668",
    "total_running_length": "42945.9969797",
    "total_emergency_stop_counts": "0",
    "total_emergency_stop_duration": "0",
    "total_take_over_counts": "0",
    "total_take_over_duration": "0",
    "total_bag_size": "0",
    "total_fault_counts": "0",
    "total_accident_counts": "0",
    "day": "20190123",
    "create_time": "1583061678"
  },
  {
    "total_id": "201901241583061739805864UslS",
    "vehicle_id": "arts16_1",
    "park_id": "shanghai_disney",
    "total_running_time": "59687",
    "total_running_length": "46847.921227",
    "total_emergency_stop_counts": "0",
    "total_emergency_stop_duration": "0",
    "total_take_over_counts": "0",
    "total_take_over_duration": "0",
    "total_bag_size": "0",
    "total_fault_counts": "0",
    "total_accident_counts": "0",
    "day": "20190124",
    "create_time": "1583061740"
  },
  {
    "total_id": "201901251583061801603341dqeG",
    "vehicle_id": "arts16_1",
    "park_id": "shanghai_disney",
    "total_running_time": "64767",
    "total_running_length": "50802.5716635",
    "total_emergency_stop_counts": "0",
    "total_emergency_stop_duration": "0",
    "total_take_over_counts": "0",
    "total_take_over_duration": "0",
    "total_bag_size": "0",
    "total_fault_counts": "0",
    "total_accident_counts": "0",
    "day": "20190125",
    "create_time": "1583061802"
  },
  {
    "total_id": "201901261583061853312226iaYr",
    "vehicle_id": "arts16_1",
    "park_id": "shanghai_disney",
    "total_running_time": "69157",
    "total_running_length": "54748.391706",
    "total_emergency_stop_counts": "0",
    "total_emergency_stop_duration": "0",
    "total_take_over_counts": "0",
    "total_take_over_duration": "0",
    "total_bag_size": "0",
    "total_fault_counts": "0",
    "total_accident_counts": "0",
    "day": "20190126",
    "create_time": "1583061853"
  },
  {
    "total_id": "201901271583061912105111aDNX",
    "vehicle_id": "arts16_1",
    "park_id": "shanghai_disney",
    "total_running_time": "80214",
    "total_running_length": "62732.7085479",
    "total_emergency_stop_counts": "0",
    "total_emergency_stop_duration": "0",
    "total_take_over_counts": "0",
    "total_take_over_duration": "0",
    "total_bag_size": "0",
    "total_fault_counts": "0",
    "total_accident_counts": "0",
    "day": "20190127",
    "create_time": "1583061912"
  },
  {
    "total_id": "201901281583061982683950dhjb",
    "vehicle_id": "arts16_1",
    "park_id": "shanghai_disney",
    "total_running_time": "88507",
    "total_running_length": "70627.6123036",
    "total_emergency_stop_counts": "0",
    "total_emergency_stop_duration": "0",
    "total_take_over_counts": "0",
    "total_take_over_duration": "0",
    "total_bag_size": "0",
    "total_fault_counts": "0",
    "total_accident_counts": "0",
    "day": "20190128",
    "create_time": "1583061983"
  },
  {
    "total_id": "201901291583062058171743YLza",
    "vehicle_id": "arts16_1",
    "park_id": "shanghai_disney",
    "total_running_time": "96838",
    "total_running_length": "78498.9388079",
    "total_emergency_stop_counts": "0",
    "total_emergency_stop_duration": "0",
    "total_take_over_counts": "0",
    "total_take_over_duration": "0",
    "total_bag_size": "0",
    "total_fault_counts": "0",
    "total_accident_counts": "0",
    "day": "20190129",
    "create_time": "1583062058"
  },
  {
    "total_id": "201901301583062124997171ertV",
    "vehicle_id": "arts16_1",
    "park_id": "shanghai_disney",
    "total_running_time": "105836",
    "total_running_length": "81522.8179294",
    "total_emergency_stop_counts": "0",
    "total_emergency_stop_duration": "0",
    "total_take_over_counts": "0",
    "total_take_over_duration": "0",
    "total_bag_size": "0",
    "total_fault_counts": "0",
    "total_accident_counts": "0",
    "day": "20190130",
    "create_time": "1583062125"
  },
  {
    "total_id": "201901311583062208539921pUMd",
    "vehicle_id": "arts16_1",
    "park_id": "shanghai_disney",
    "total_running_time": "114399",
    "total_running_length": "85716.0824184",
    "total_emergency_stop_counts": "0",
    "total_emergency_stop_duration": "0",
    "total_take_over_counts": "0",
    "total_take_over_duration": "0",
    "total_bag_size": "0",
    "total_fault_counts": "0",
    "total_accident_counts": "0",
    "day": "20190131",
    "create_time": "1583062209"
  },
  {
    "total_id": "201902011583062307752894EHXF",
    "vehicle_id": "arts16_1",
    "park_id": "shanghai_disney",
    "total_running_time": "128432",
    "total_running_length": "90964.1359943",
    "total_emergency_stop_counts": "0",
    "total_emergency_stop_duration": "0",
    "total_take_over_counts": "0",
    "total_take_over_duration": "0",
    "total_bag_size": "0",
    "total_fault_counts": "0",
    "total_accident_counts": "0",
    "day": "20190201",
    "create_time": "1583062308"
  },
  {
    "total_id": "201902021583062388469019eHZc",
    "vehicle_id": "arts16_1",
    "park_id": "shanghai_disney",
    "total_running_time": "135291",
    "total_running_length": "96787.0182889",
    "total_emergency_stop_counts": "0",
    "total_emergency_stop_duration": "0",
    "total_take_over_counts": "0",
    "total_take_over_duration": "0",
    "total_bag_size": "0",
    "total_fault_counts": "0",
    "total_accident_counts": "0",
    "day": "20190202",
    "create_time": "1583062389"
  },
  {
    "total_id": "201902031583062458496096mFVp",
    "vehicle_id": "arts16_1",
    "park_id": "shanghai_disney",
    "total_running_time": "139845",
    "total_running_length": "99586.3410998",
    "total_emergency_stop_counts": "0",
    "total_emergency_stop_duration": "0",
    "total_take_over_counts": "0",
    "total_take_over_duration": "0",
    "total_bag_size": "0",
    "total_fault_counts": "0",
    "total_accident_counts": "0",
    "day": "20190203",
    "create_time": "1583062459"
  },
  {
    "total_id": "201902041583062548968444EeHu",
    "vehicle_id": "arts16_1",
    "park_id": "shanghai_disney",
    "total_running_time": "149248",
    "total_running_length": "106896.595805",
    "total_emergency_stop_counts": "0",
    "total_emergency_stop_duration": "0",
    "total_take_over_counts": "0",
    "total_take_over_duration": "0",
    "total_bag_size": "0",
    "total_fault_counts": "0",
    "total_accident_counts": "0",
    "day": "20190204",
    "create_time": "1583062549"
  },
  {
    "total_id": "201902051583062627618404KajN",
    "vehicle_id": "arts16_1",
    "park_id": "shanghai_disney",
    "total_running_time": "152148",
    "total_running_length": "109415.152606",
    "total_emergency_stop_counts": "0",
    "total_emergency_stop_duration": "0",
    "total_take_over_counts": "0",
    "total_take_over_duration": "0",
    "total_bag_size": "0",
    "total_fault_counts": "0",
    "total_accident_counts": "0",
    "day": "20190205",
    "create_time": "1583062628"
  },
  {
    "total_id": "201902061583062702665869VfqJ",
    "vehicle_id": "arts16_1",
    "park_id": "shanghai_disney",
    "total_running_time": "153855",
    "total_running_length": "111139.718483",
    "total_emergency_stop_counts": "0",
    "total_emergency_stop_duration": "0",
    "total_take_over_counts": "0",
    "total_take_over_duration": "0",
    "total_bag_size": "0",
    "total_fault_counts": "0",
    "total_accident_counts": "0",
    "day": "20190206",
    "create_time": "1583062703"
  },
  {
    "total_id": "201902071583062789452956mCsl",
    "vehicle_id": "arts16_1",
    "park_id": "shanghai_disney",
    "total_running_time": "163515",
    "total_running_length": "117953.126005",
    "total_emergency_stop_counts": "0",
    "total_emergency_stop_duration": "0",
    "total_take_over_counts": "0",
    "total_take_over_duration": "0",
    "total_bag_size": "0",
    "total_fault_counts": "0",
    "total_accident_counts": "0",
    "day": "20190207",
    "create_time": "1583062789"
  },
  {
    "total_id": "201902081583062860486733Iwil",
    "vehicle_id": "arts16_1",
    "park_id": "shanghai_disney",
    "total_running_time": "166853",
    "total_running_length": "120008.548685",
    "total_emergency_stop_counts": "0",
    "total_emergency_stop_duration": "0",
    "total_take_over_counts": "0",
    "total_take_over_duration": "0",
    "total_bag_size": "0",
    "total_fault_counts": "0",
    "total_accident_counts": "0",
    "day": "20190208",
    "create_time": "1583062861"
  },
  {
    "total_id": "201902091583062936861314mTSC",
    "vehicle_id": "arts16_1",
    "park_id": "shanghai_disney",
    "total_running_time": "170020",
    "total_running_length": "123281.073162",
    "total_emergency_stop_counts": "0",
    "total_emergency_stop_duration": "0",
    "total_take_over_counts": "0",
    "total_take_over_duration": "0",
    "total_bag_size": "0",
    "total_fault_counts": "0",
    "total_accident_counts": "0",
    "day": "20190209",
    "create_time": "1583062937"
  },
  {
    "total_id": "201902101583063016066233RLan",
    "vehicle_id": "arts16_1",
    "park_id": "shanghai_disney",
    "total_running_time": "180371",
    "total_running_length": "129392.224039",
    "total_emergency_stop_counts": "0",
    "total_emergency_stop_duration": "0",
    "total_take_over_counts": "0",
    "total_take_over_duration": "0",
    "total_bag_size": "0",
    "total_fault_counts": "0",
    "total_accident_counts": "0",
    "day": "20190210",
    "create_time": "1583063016"
  },
  {
    "total_id": "201902111583063107212773LSwl",
    "vehicle_id": "arts16_1",
    "park_id": "shanghai_disney",
    "total_running_time": "186553",
    "total_running_length": "133315.271805",
    "total_emergency_stop_counts": "0",
    "total_emergency_stop_duration": "0",
    "total_take_over_counts": "0",
    "total_take_over_duration": "0",
    "total_bag_size": "0",
    "total_fault_counts": "0",
    "total_accident_counts": "0",
    "day": "20190211",
    "create_time": "1583063107"
  },
  {
    "total_id": "201902121583063183733277vHwy",
    "vehicle_id": "arts16_1",
    "park_id": "shanghai_disney",
    "total_running_time": "188467",
    "total_running_length": "135280.866825",
    "total_emergency_stop_counts": "0",
    "total_emergency_stop_duration": "0",
    "total_take_over_counts": "0",
    "total_take_over_duration": "0",
    "total_bag_size": "0",
    "total_fault_counts": "0",
    "total_accident_counts": "0",
    "day": "20190212",
    "create_time": "1583063184"
  },
  {
    "total_id": "201902141583063330604272ObIh",
    "vehicle_id": "arts16_1",
    "park_id": "shanghai_disney",
    "total_running_time": "192818",
    "total_running_length": "138107.967401",
    "total_emergency_stop_counts": "0",
    "total_emergency_stop_duration": "0",
    "total_take_over_counts": "0",
    "total_take_over_duration": "0",
    "total_bag_size": "0",
    "total_fault_counts": "0",
    "total_accident_counts": "0",
    "day": "20190214",
    "create_time": "1583063331"
  },
  {
    "total_id": "201902151583063400183383VzzK",
    "vehicle_id": "arts16_1",
    "park_id": "shanghai_disney",
    "total_running_time": "197000",
    "total_running_length": "139734.797731",
    "total_emergency_stop_counts": "0",
    "total_emergency_stop_duration": "0",
    "total_take_over_counts": "0",
    "total_take_over_duration": "0",
    "total_bag_size": "0",
    "total_fault_counts": "0",
    "total_accident_counts": "0",
    "day": "20190215",
    "create_time": "1583063400"
  },
  {
    "total_id": "201902161583063485048182YmuB",
    "vehicle_id": "arts16_1",
    "park_id": "shanghai_disney",
    "total_running_time": "201407",
    "total_running_length": "142164.994321",
    "total_emergency_stop_counts": "0",
    "total_emergency_stop_duration": "0",
    "total_take_over_counts": "0",
    "total_take_over_duration": "0",
    "total_bag_size": "0",
    "total_fault_counts": "0",
    "total_accident_counts": "0",
    "day": "20190216",
    "create_time": "1583063485"
  },
  {
    "total_id": "201902171583063558280867MGxY",
    "vehicle_id": "arts16_1",
    "park_id": "shanghai_disney",
    "total_running_time": "206516",
    "total_running_length": "145837.012176",
    "total_emergency_stop_counts": "0",
    "total_emergency_stop_duration": "0",
    "total_take_over_counts": "0",
    "total_take_over_duration": "0",
    "total_bag_size": "0",
    "total_fault_counts": "0",
    "total_accident_counts": "0",
    "day": "20190217",
    "create_time": "1583063558"
  },
  {
    "total_id": "201902181583063621835441GnCE",
    "vehicle_id": "arts16_1",
    "park_id": "shanghai_disney",
    "total_running_time": "208325",
    "total_running_length": "147661.293186",
    "total_emergency_stop_counts": "0",
    "total_emergency_stop_duration": "0",
    "total_take_over_counts": "0",
    "total_take_over_duration": "0",
    "total_bag_size": "0",
    "total_fault_counts": "0",
    "total_accident_counts": "0",
    "day": "20190218",
    "create_time": "1583063622"
  },
  {
    "total_id": "201902211583063821329395dEYL",
    "vehicle_id": "arts16_1",
    "park_id": "shanghai_disney",
    "total_running_time": "217668",
    "total_running_length": "152750.59978",
    "total_emergency_stop_counts": "0",
    "total_emergency_stop_duration": "0",
    "total_take_over_counts": "0",
    "total_take_over_duration": "0",
    "total_bag_size": "0",
    "total_fault_counts": "0",
    "total_accident_counts": "0",
    "day": "20190221",
    "create_time": "1583063821"
  },
  {
    "total_id": "201902221583063896330955maQJ",
    "vehicle_id": "arts16_1",
    "park_id": "shanghai_disney",
    "total_running_time": "222221",
    "total_running_length": "155781.839025",
    "total_emergency_stop_counts": "0",
    "total_emergency_stop_duration": "0",
    "total_take_over_counts": "0",
    "total_take_over_duration": "0",
    "total_bag_size": "0",
    "total_fault_counts": "0",
    "total_accident_counts": "0",
    "day": "20190222",
    "create_time": "1583063896"
  },
  {
    "total_id": "201902251583064116305996mwzA",
    "vehicle_id": "arts16_1",
    "park_id": "shanghai_disney",
    "total_running_time": "228875",
    "total_running_length": "161723.137521",
    "total_emergency_stop_counts": "0",
    "total_emergency_stop_duration": "0",
    "total_take_over_counts": "0",
    "total_take_over_duration": "0",
    "total_bag_size": "0",
    "total_fault_counts": "0",
    "total_accident_counts": "0",
    "day": "20190225",
    "create_time": "1583064116"
  },
  {
    "total_id": "201902261583064181369708owcM",
    "vehicle_id": "arts16_1",
    "park_id": "shanghai_disney",
    "total_running_time": "234861",
    "total_running_length": "165592.167804",
    "total_emergency_stop_counts": "0",
    "total_emergency_stop_duration": "0",
    "total_take_over_counts": "0",
    "total_take_over_duration": "0",
    "total_bag_size": "0",
    "total_fault_counts": "0",
    "total_accident_counts": "0",
    "day": "20190226",
    "create_time": "1583064181"
  },
  {
    "total_id": "201902271583064254259226wQMs",
    "vehicle_id": "arts16_1",
    "park_id": "shanghai_disney",
    "total_running_time": "238766",
    "total_running_length": "169548.19237",
    "total_emergency_stop_counts": "0",
    "total_emergency_stop_duration": "0",
    "total_take_over_counts": "0",
    "total_take_over_duration": "0",
    "total_bag_size": "0",
    "total_fault_counts": "0",
    "total_accident_counts": "0",
    "day": "20190227",
    "create_time": "1583064254"
  },
  {
    "total_id": "201902281583064327979006wVBR",
    "vehicle_id": "arts16_1",
    "park_id": "shanghai_disney",
    "total_running_time": "244692",
    "total_running_length": "174537.868113",
    "total_emergency_stop_counts": "0",
    "total_emergency_stop_duration": "0",
    "total_take_over_counts": "0",
    "total_take_over_duration": "0",
    "total_bag_size": "0",
    "total_fault_counts": "0",
    "total_accident_counts": "0",
    "day": "20190228",
    "create_time": "1583064328"
  },
  {
    "total_id": "201903011583064401858611vJLZ",
    "vehicle_id": "arts16_1",
    "park_id": "shanghai_disney",
    "total_running_time": "249112",
    "total_running_length": "177111.296685",
    "total_emergency_stop_counts": "0",
    "total_emergency_stop_duration": "0",
    "total_take_over_counts": "0",
    "total_take_over_duration": "0",
    "total_bag_size": "0",
    "total_fault_counts": "0",
    "total_accident_counts": "0",
    "day": "20190301",
    "create_time": "1583064402"
  },
  {
    "total_id": "201903021583064477551422eChl",
    "vehicle_id": "arts16_1",
    "park_id": "shanghai_disney",
    "total_running_time": "254024",
    "total_running_length": "181609.799086",
    "total_emergency_stop_counts": "0",
    "total_emergency_stop_duration": "0",
    "total_take_over_counts": "0",
    "total_take_over_duration": "0",
    "total_bag_size": "0",
    "total_fault_counts": "0",
    "total_accident_counts": "0",
    "day": "20190302",
    "create_time": "1583064478"
  },
  {
    "total_id": "201903031583064554342342qPKh",
    "vehicle_id": "arts16_1",
    "park_id": "shanghai_disney",
    "total_running_time": "257944",
    "total_running_length": "184967.948285",
    "total_emergency_stop_counts": "0",
    "total_emergency_stop_duration": "0",
    "total_take_over_counts": "0",
    "total_take_over_duration": "0",
    "total_bag_size": "0",
    "total_fault_counts": "0",
    "total_accident_counts": "0",
    "day": "20190303",
    "create_time": "1583064554"
  },
  {
    "total_id": "201903041583064632556705vRdp",
    "vehicle_id": "arts16_1",
    "park_id": "shanghai_disney",
    "total_running_time": "263350",
    "total_running_length": "188727.396703",
    "total_emergency_stop_counts": "0",
    "total_emergency_stop_duration": "0",
    "total_take_over_counts": "0",
    "total_take_over_duration": "0",
    "total_bag_size": "0",
    "total_fault_counts": "0",
    "total_accident_counts": "0",
    "day": "20190304",
    "create_time": "1583064633"
  },
  {
    "total_id": "201903051583064706982006aXgS",
    "vehicle_id": "arts16_1",
    "park_id": "shanghai_disney",
    "total_running_time": "269019",
    "total_running_length": "194205.584787",
    "total_emergency_stop_counts": "0",
    "total_emergency_stop_duration": "0",
    "total_take_over_counts": "0",
    "total_take_over_duration": "0",
    "total_bag_size": "0",
    "total_fault_counts": "0",
    "total_accident_counts": "0",
    "day": "20190305",
    "create_time": "1583064707"
  },
  {
    "total_id": "201903061583064781514082WRKu",
    "vehicle_id": "arts16_1",
    "park_id": "shanghai_disney",
    "total_running_time": "272922",
    "total_running_length": "198040.207591",
    "total_emergency_stop_counts": "0",
    "total_emergency_stop_duration": "0",
    "total_take_over_counts": "0",
    "total_take_over_duration": "0",
    "total_bag_size": "0",
    "total_fault_counts": "0",
    "total_accident_counts": "0",
    "day": "20190306",
    "create_time": "1583064782"
  },
  {
    "total_id": "201903071583064850307679Csgm",
    "vehicle_id": "arts16_1",
    "park_id": "shanghai_disney",
    "total_running_time": "274970",
    "total_running_length": "200094.030588",
    "total_emergency_stop_counts": "0",
    "total_emergency_stop_duration": "0",
    "total_take_over_counts": "0",
    "total_take_over_duration": "0",
    "total_bag_size": "0",
    "total_fault_counts": "0",
    "total_accident_counts": "0",
    "day": "20190307",
    "create_time": "1583064850"
  },
  {
    "total_id": "201903081583064920536274qDfM",
    "vehicle_id": "arts16_1",
    "park_id": "shanghai_disney",
    "total_running_time": "281257",
    "total_running_length": "206084.704267",
    "total_emergency_stop_counts": "0",
    "total_emergency_stop_duration": "0",
    "total_take_over_counts": "0",
    "total_take_over_duration": "0",
    "total_bag_size": "0",
    "total_fault_counts": "0",
    "total_accident_counts": "0",
    "day": "20190308",
    "create_time": "1583064921"
  },
  {
    "total_id": "201903091583064997159906gpad",
    "vehicle_id": "arts16_1",
    "park_id": "shanghai_disney",
    "total_running_time": "286033",
    "total_running_length": "209667.304218",
    "total_emergency_stop_counts": "0",
    "total_emergency_stop_duration": "0",
    "total_take_over_counts": "0",
    "total_take_over_duration": "0",
    "total_bag_size": "0",
    "total_fault_counts": "0",
    "total_accident_counts": "0",
    "day": "20190309",
    "create_time": "1583064997"
  },
  {
    "total_id": "201903101583065071882805NhKn",
    "vehicle_id": "arts16_1",
    "park_id": "shanghai_disney",
    "total_running_time": "291636",
    "total_running_length": "213604.608546",
    "total_emergency_stop_counts": "0",
    "total_emergency_stop_duration": "0",
    "total_take_over_counts": "0",
    "total_take_over_duration": "0",
    "total_bag_size": "0",
    "total_fault_counts": "0",
    "total_accident_counts": "0",
    "day": "20190310",
    "create_time": "1583065072"
  },
  {
    "total_id": "201903111583065152858709IbpS",
    "vehicle_id": "arts16_1",
    "park_id": "shanghai_disney",
    "total_running_time": "296351",
    "total_running_length": "217896.29213",
    "total_emergency_stop_counts": "0",
    "total_emergency_stop_duration": "0",
    "total_take_over_counts": "0",
    "total_take_over_duration": "0",
    "total_bag_size": "0",
    "total_fault_counts": "0",
    "total_accident_counts": "0",
    "day": "20190311",
    "create_time": "1583065153"
  },
  {
    "total_id": "201903121583065230777884BNCp",
    "vehicle_id": "arts16_1",
    "park_id": "shanghai_disney",
    "total_running_time": "301289",
    "total_running_length": "222494.534374",
    "total_emergency_stop_counts": "0",
    "total_emergency_stop_duration": "0",
    "total_take_over_counts": "0",
    "total_take_over_duration": "0",
    "total_bag_size": "0",
    "total_fault_counts": "0",
    "total_accident_counts": "0",
    "day": "20190312",
    "create_time": "1583065231"
  },
  {
    "total_id": "201903131583065306940214Xzyf",
    "vehicle_id": "arts16_1",
    "park_id": "shanghai_disney",
    "total_running_time": "305485",
    "total_running_length": "226648.119782",
    "total_emergency_stop_counts": "0",
    "total_emergency_stop_duration": "0",
    "total_take_over_counts": "0",
    "total_take_over_duration": "0",
    "total_bag_size": "0",
    "total_fault_counts": "0",
    "total_accident_counts": "0",
    "day": "20190313",
    "create_time": "1583065307"
  },
  {
    "total_id": "201903141583065381092107PgTC",
    "vehicle_id": "arts16_1",
    "park_id": "shanghai_disney",
    "total_running_time": "309632",
    "total_running_length": "230729.227919",
    "total_emergency_stop_counts": "0",
    "total_emergency_stop_duration": "0",
    "total_take_over_counts": "0",
    "total_take_over_duration": "0",
    "total_bag_size": "0",
    "total_fault_counts": "0",
    "total_accident_counts": "0",
    "day": "20190314",
    "create_time": "1583065381"
  },
  {
    "total_id": "201903151583065454151731YJNH",
    "vehicle_id": "arts16_1",
    "park_id": "shanghai_disney",
    "total_running_time": "314171",
    "total_running_length": "234926.172134",
    "total_emergency_stop_counts": "0",
    "total_emergency_stop_duration": "0",
    "total_take_over_counts": "0",
    "total_take_over_duration": "0",
    "total_bag_size": "0",
    "total_fault_counts": "0",
    "total_accident_counts": "0",
    "day": "20190315",
    "create_time": "1583065454"
  },
  {
    "total_id": "201903161583065537561083mMnY",
    "vehicle_id": "arts16_1",
    "park_id": "shanghai_disney",
    "total_running_time": "317955",
    "total_running_length": "238949.9231",
    "total_emergency_stop_counts": "0",
    "total_emergency_stop_duration": "0",
    "total_take_over_counts": "0",
    "total_take_over_duration": "0",
    "total_bag_size": "0",
    "total_fault_counts": "0",
    "total_accident_counts": "0",
    "day": "20190316",
    "create_time": "1583065538"
  },
  {
    "total_id": "201903171583065607648000LzYM",
    "vehicle_id": "arts16_1",
    "park_id": "shanghai_disney",
    "total_running_time": "321752",
    "total_running_length": "242898.595073",
    "total_emergency_stop_counts": "0",
    "total_emergency_stop_duration": "0",
    "total_take_over_counts": "0",
    "total_take_over_duration": "0",
    "total_bag_size": "0",
    "total_fault_counts": "0",
    "total_accident_counts": "0",
    "day": "20190317",
    "create_time": "1583065608"
  },
  {
    "total_id": "201903181583066031372331Mhiw",
    "vehicle_id": "arts16_1",
    "park_id": "shanghai_disney",
    "total_running_time": "325617",
    "total_running_length": "246889.131857",
    "total_emergency_stop_counts": "0",
    "total_emergency_stop_duration": "0",
    "total_take_over_counts": "0",
    "total_take_over_duration": "0",
    "total_bag_size": "0",
    "total_fault_counts": "0",
    "total_accident_counts": "0",
    "day": "20190318",
    "create_time": "1583066031"
  },
  {
    "total_id": "201903191583066109836264Agyf",
    "vehicle_id": "arts16_1",
    "park_id": "shanghai_disney",
    "total_running_time": "329802",
    "total_running_length": "251203.144388",
    "total_emergency_stop_counts": "0",
    "total_emergency_stop_duration": "0",
    "total_take_over_counts": "0",
    "total_take_over_duration": "0",
    "total_bag_size": "0",
    "total_fault_counts": "0",
    "total_accident_counts": "0",
    "day": "20190319",
    "create_time": "1583066110"
  },
  {
    "total_id": "201903201583066186270920WFku",
    "vehicle_id": "arts16_1",
    "park_id": "shanghai_disney",
    "total_running_time": "333356",
    "total_running_length": "254997.464272",
    "total_emergency_stop_counts": "0",
    "total_emergency_stop_duration": "0",
    "total_take_over_counts": "0",
    "total_take_over_duration": "0",
    "total_bag_size": "0",
    "total_fault_counts": "0",
    "total_accident_counts": "0",
    "day": "20190320",
    "create_time": "1583066186"
  },
  {
    "total_id": "201903211583066255263572HcmR",
    "vehicle_id": "arts16_1",
    "park_id": "shanghai_disney",
    "total_running_time": "335510",
    "total_running_length": "257222.680916",
    "total_emergency_stop_counts": "0",
    "total_emergency_stop_duration": "0",
    "total_take_over_counts": "0",
    "total_take_over_duration": "0",
    "total_bag_size": "0",
    "total_fault_counts": "0",
    "total_accident_counts": "0",
    "day": "20190321",
    "create_time": "1583066255"
  },
  {
    "total_id": "201903221583066319858837auhJ",
    "vehicle_id": "arts16_1",
    "park_id": "shanghai_disney",
    "total_running_time": "339973",
    "total_running_length": "261753.036893",
    "total_emergency_stop_counts": "0",
    "total_emergency_stop_duration": "0",
    "total_take_over_counts": "0",
    "total_take_over_duration": "0",
    "total_bag_size": "0",
    "total_fault_counts": "0",
    "total_accident_counts": "0",
    "day": "20190322",
    "create_time": "1583066320"
  },
  {
    "total_id": "201903231583066380494676wDZP",
    "vehicle_id": "arts16_1",
    "park_id": "shanghai_disney",
    "total_running_time": "345819",
    "total_running_length": "267744.505643",
    "total_emergency_stop_counts": "0",
    "total_emergency_stop_duration": "0",
    "total_take_over_counts": "0",
    "total_take_over_duration": "0",
    "total_bag_size": "0",
    "total_fault_counts": "0",
    "total_accident_counts": "0",
    "day": "20190323",
    "create_time": "1583066381"
  },
  {
    "total_id": "201903241583066434810209Uppz",
    "vehicle_id": "arts16_1",
    "park_id": "shanghai_disney",
    "total_running_time": "348601",
    "total_running_length": "269626.885619",
    "total_emergency_stop_counts": "0",
    "total_emergency_stop_duration": "0",
    "total_take_over_counts": "0",
    "total_take_over_duration": "0",
    "total_bag_size": "0",
    "total_fault_counts": "0",
    "total_accident_counts": "0",
    "day": "20190324",
    "create_time": "1583066435"
  },
  {
    "total_id": "201903251583066496739384JrtE",
    "vehicle_id": "arts16_1",
    "park_id": "shanghai_disney",
    "total_running_time": "352671",
    "total_running_length": "273649.675378",
    "total_emergency_stop_counts": "0",
    "total_emergency_stop_duration": "0",
    "total_take_over_counts": "0",
    "total_take_over_duration": "0",
    "total_bag_size": "0",
    "total_fault_counts": "0",
    "total_accident_counts": "0",
    "day": "20190325",
    "create_time": "1583066497"
  },
  {
    "total_id": "201903261583066561727869mNQT",
    "vehicle_id": "arts16_1",
    "park_id": "shanghai_disney",
    "total_running_time": "358802",
    "total_running_length": "278664.624714",
    "total_emergency_stop_counts": "0",
    "total_emergency_stop_duration": "0",
    "total_take_over_counts": "0",
    "total_take_over_duration": "0",
    "total_bag_size": "0",
    "total_fault_counts": "0",
    "total_accident_counts": "0",
    "day": "20190326",
    "create_time": "1583066562"
  },
  {
    "total_id": "201903271583066629315594ohZz",
    "vehicle_id": "arts16_1",
    "park_id": "shanghai_disney",
    "total_running_time": "361776",
    "total_running_length": "281596.391053",
    "total_emergency_stop_counts": "0",
    "total_emergency_stop_duration": "0",
    "total_take_over_counts": "0",
    "total_take_over_duration": "0",
    "total_bag_size": "0",
    "total_fault_counts": "0",
    "total_accident_counts": "0",
    "day": "20190327",
    "create_time": "1583066629"
  },
  {
    "total_id": "201905141583069507397755Loli",
    "vehicle_id": "arts16_1",
    "park_id": "shanghai_disney",
    "total_running_time": "365943",
    "total_running_length": "286029.171746",
    "total_emergency_stop_counts": "0",
    "total_emergency_stop_duration": "0",
    "total_take_over_counts": "0",
    "total_take_over_duration": "0",
    "total_bag_size": "0",
    "total_fault_counts": "0",
    "total_accident_counts": "0",
    "day": "20190514",
    "create_time": "1583069507"
  },
  {
    "total_id": "201905151583069564064338sfrc",
    "vehicle_id": "arts16_1",
    "park_id": "shanghai_disney",
    "total_running_time": "370538",
    "total_running_length": "290411.39598",
    "total_emergency_stop_counts": "0",
    "total_emergency_stop_duration": "0",
    "total_take_over_counts": "0",
    "total_take_over_duration": "0",
    "total_bag_size": "0",
    "total_fault_counts": "0",
    "total_accident_counts": "0",
    "day": "20190515",
    "create_time": "1583069564"
  },
  {
    "total_id": "201905191583069811463381KksD",
    "vehicle_id": "arts16_1",
    "park_id": "shanghai_disney",
    "total_running_time": "372895",
    "total_running_length": "291765.763961",
    "total_emergency_stop_counts": "0",
    "total_emergency_stop_duration": "0",
    "total_take_over_counts": "0",
    "total_take_over_duration": "0",
    "total_bag_size": "0",
    "total_fault_counts": "0",
    "total_accident_counts": "0",
    "day": "20190519",
    "create_time": "1583069812"
  },
  {
    "total_id": "201905201583069873928087kiuP",
    "vehicle_id": "arts16_1",
    "park_id": "shanghai_disney",
    "total_running_time": "379466",
    "total_running_length": "298350.623037",
    "total_emergency_stop_counts": "0",
    "total_emergency_stop_duration": "0",
    "total_take_over_counts": "0",
    "total_take_over_duration": "0",
    "total_bag_size": "0",
    "total_fault_counts": "0",
    "total_accident_counts": "0",
    "day": "20190520",
    "create_time": "1583069874"
  },
  {
    "total_id": "201905211583069945747471oxKA",
    "vehicle_id": "arts16_1",
    "park_id": "shanghai_disney",
    "total_running_time": "382253",
    "total_running_length": "300984.763073",
    "total_emergency_stop_counts": "0",
    "total_emergency_stop_duration": "0",
    "total_take_over_counts": "0",
    "total_take_over_duration": "0",
    "total_bag_size": "0",
    "total_fault_counts": "0",
    "total_accident_counts": "0",
    "day": "20190521",
    "create_time": "1583069946"
  },
  {
    "total_id": "201905221583070020158190Iktq",
    "vehicle_id": "arts16_1",
    "park_id": "shanghai_disney",
    "total_running_time": "387151",
    "total_running_length": "306057.83238",
    "total_emergency_stop_counts": "0",
    "total_emergency_stop_duration": "0",
    "total_take_over_counts": "0",
    "total_take_over_duration": "0",
    "total_bag_size": "0",
    "total_fault_counts": "0",
    "total_accident_counts": "0",
    "day": "20190522",
    "create_time": "1583070020"
  },
  {
    "total_id": "201905231583070081720064AbwL",
    "vehicle_id": "arts16_1",
    "park_id": "shanghai_disney",
    "total_running_time": "390197",
    "total_running_length": "309003.358961",
    "total_emergency_stop_counts": "0",
    "total_emergency_stop_duration": "0",
    "total_take_over_counts": "0",
    "total_take_over_duration": "0",
    "total_bag_size": "0",
    "total_fault_counts": "0",
    "total_accident_counts": "0",
    "day": "20190523",
    "create_time": "1583070082"
  },
  {
    "total_id": "201905241583070136962424esPD",
    "vehicle_id": "arts16_1",
    "park_id": "shanghai_disney",
    "total_running_time": "393060",
    "total_running_length": "311819.255669",
    "total_emergency_stop_counts": "0",
    "total_emergency_stop_duration": "0",
    "total_take_over_counts": "0",
    "total_take_over_duration": "0",
    "total_bag_size": "0",
    "total_fault_counts": "0",
    "total_accident_counts": "0",
    "day": "20190524",
    "create_time": "1583070137"
  },
  {
    "total_id": "201906251583072389603994VqZx",
    "vehicle_id": "arts16_1",
    "park_id": "jiading_innovation_port",
    "total_running_time": "8906",
    "total_running_length": "5123.79780702",
    "total_emergency_stop_counts": "0",
    "total_emergency_stop_duration": "0",
    "total_take_over_counts": "17",
    "total_take_over_duration": "606.805411101",
    "total_bag_size": "0",
    "total_fault_counts": "0",
    "total_accident_counts": "0",
    "day": "20190625",
    "create_time": "1583072390"
  },
  {
    "total_id": "201906261583072445190111iPRr",
    "vehicle_id": "arts16_1",
    "park_id": "jiading_innovation_port",
    "total_running_time": "14803",
    "total_running_length": "10829.8610327",
    "total_emergency_stop_counts": "0",
    "total_emergency_stop_duration": "0",
    "total_take_over_counts": "21",
    "total_take_over_duration": "736.638251109",
    "total_bag_size": "0",
    "total_fault_counts": "0",
    "total_accident_counts": "0",
    "day": "20190626",
    "create_time": "1583072445"
  },
  {
    "total_id": "201906271583072514475162JfSl",
    "vehicle_id": "arts16_1",
    "park_id": "jiading_innovation_port",
    "total_running_time": "21473",
    "total_running_length": "17029.3717132",
    "total_emergency_stop_counts": "0",
    "total_emergency_stop_duration": "0",
    "total_take_over_counts": "26",
    "total_take_over_duration": "790.625104486",
    "total_bag_size": "0",
    "total_fault_counts": "0",
    "total_accident_counts": "0",
    "day": "20190627",
    "create_time": "1583072515"
  },
  {
    "total_id": "201906281583072581653626dWrr",
    "vehicle_id": "arts16_1",
    "park_id": "jiading_innovation_port",
    "total_running_time": "25972",
    "total_running_length": "20153.8024133",
    "total_emergency_stop_counts": "0",
    "total_emergency_stop_duration": "0",
    "total_take_over_counts": "31",
    "total_take_over_duration": "1192.29995922",
    "total_bag_size": "0",
    "total_fault_counts": "0",
    "total_accident_counts": "0",
    "day": "20190628",
    "create_time": "1583072582"
  },
  {
    "total_id": "201906291583072652913252qAvW",
    "vehicle_id": "arts16_1",
    "park_id": "jiading_innovation_port",
    "total_running_time": "31505",
    "total_running_length": "26229.6216313",
    "total_emergency_stop_counts": "0",
    "total_emergency_stop_duration": "0",
    "total_take_over_counts": "31",
    "total_take_over_duration": "1192.29995922",
    "total_bag_size": "0",
    "total_fault_counts": "0",
    "total_accident_counts": "0",
    "day": "20190629",
    "create_time": "1583072653"
  },
  {
    "total_id": "201906301583072709888519TOFN",
    "vehicle_id": "arts16_1",
    "park_id": "jiading_innovation_port",
    "total_running_time": "37193",
    "total_running_length": "32249.8641434",
    "total_emergency_stop_counts": "0",
    "total_emergency_stop_duration": "0",
    "total_take_over_counts": "34",
    "total_take_over_duration": "1244.37584744",
    "total_bag_size": "0",
    "total_fault_counts": "0",
    "total_accident_counts": "0",
    "day": "20190630",
    "create_time": "1583072710"
  },
  {
    "total_id": "201907011583072769871036Rkti",
    "vehicle_id": "arts16_1",
    "park_id": "jiading_innovation_port",
    "total_running_time": "41399",
    "total_running_length": "36409.3492327",
    "total_emergency_stop_counts": "0",
    "total_emergency_stop_duration": "0",
    "total_take_over_counts": "35",
    "total_take_over_duration": "1248.36766466",
    "total_bag_size": "0",
    "total_fault_counts": "0",
    "total_accident_counts": "0",
    "day": "20190701",
    "create_time": "1583072770"
  },
  {
    "total_id": "201907021583072836601602Lmsg",
    "vehicle_id": "arts16_1",
    "park_id": "jiading_innovation_port",
    "total_running_time": "47919",
    "total_running_length": "42376.1511031",
    "total_emergency_stop_counts": "0",
    "total_emergency_stop_duration": "0",
    "total_take_over_counts": "38",
    "total_take_over_duration": "1302.08469743",
    "total_bag_size": "0",
    "total_fault_counts": "0",
    "total_accident_counts": "0",
    "day": "20190702",
    "create_time": "1583072837"
  },
  {
    "total_id": "201907031583072904128754VsWA",
    "vehicle_id": "arts16_1",
    "park_id": "jiading_innovation_port",
    "total_running_time": "53658",
    "total_running_length": "48592.5840941",
    "total_emergency_stop_counts": "0",
    "total_emergency_stop_duration": "0",
    "total_take_over_counts": "38",
    "total_take_over_duration": "1302.08469743",
    "total_bag_size": "0",
    "total_fault_counts": "0",
    "total_accident_counts": "0",
    "day": "20190703",
    "create_time": "1583072904"
  },
  {
    "total_id": "201907041583072980332383ydAJ",
    "vehicle_id": "arts16_1",
    "park_id": "jiading_innovation_port",
    "total_running_time": "59305",
    "total_running_length": "54608.9102463",
    "total_emergency_stop_counts": "0",
    "total_emergency_stop_duration": "0",
    "total_take_over_counts": "41",
    "total_take_over_duration": "1377.9691379",
    "total_bag_size": "0",
    "total_fault_counts": "0",
    "total_accident_counts": "0",
    "day": "20190704",
    "create_time": "1583072980"
  },
  {
    "total_id": "201907051583073054809675xynL",
    "vehicle_id": "arts16_1",
    "park_id": "jiading_innovation_port",
    "total_running_time": "64948",
    "total_running_length": "60629.7114192",
    "total_emergency_stop_counts": "0",
    "total_emergency_stop_duration": "0",
    "total_take_over_counts": "43",
    "total_take_over_duration": "1425.97053346",
    "total_bag_size": "0",
    "total_fault_counts": "0",
    "total_accident_counts": "0",
    "day": "20190705",
    "create_time": "1583073055"
  },
  {
    "total_id": "201907061583073127279032dzIZ",
    "vehicle_id": "arts16_1",
    "park_id": "jiading_innovation_port",
    "total_running_time": "70702",
    "total_running_length": "66492.3119292",
    "total_emergency_stop_counts": "0",
    "total_emergency_stop_duration": "0",
    "total_take_over_counts": "43",
    "total_take_over_duration": "1425.97053346",
    "total_bag_size": "0",
    "total_fault_counts": "0",
    "total_accident_counts": "0",
    "day": "20190706",
    "create_time": "1583073127"
  },
  {
    "total_id": "201907071583073194915006gVRw",
    "vehicle_id": "arts16_1",
    "park_id": "jiading_innovation_port",
    "total_running_time": "77280",
    "total_running_length": "72549.976356",
    "total_emergency_stop_counts": "0",
    "total_emergency_stop_duration": "0",
    "total_take_over_counts": "45",
    "total_take_over_duration": "1429.95765617",
    "total_bag_size": "0",
    "total_fault_counts": "0",
    "total_accident_counts": "0",
    "day": "20190707",
    "create_time": "1583073195"
  },
  {
    "total_id": "201907081583073268380385VqND",
    "vehicle_id": "arts16_1",
    "park_id": "jiading_innovation_port",
    "total_running_time": "82965",
    "total_running_length": "78455.3004207",
    "total_emergency_stop_counts": "0",
    "total_emergency_stop_duration": "0",
    "total_take_over_counts": "45",
    "total_take_over_duration": "1429.95765617",
    "total_bag_size": "0",
    "total_fault_counts": "0",
    "total_accident_counts": "0",
    "day": "20190708",
    "create_time": "1583073268"
  },
  {
    "total_id": "201907111583073468070369FrxC",
    "vehicle_id": "arts16_1",
    "park_id": "jiading_innovation_port",
    "total_running_time": "88652",
    "total_running_length": "84359.7479139",
    "total_emergency_stop_counts": "0",
    "total_emergency_stop_duration": "0",
    "total_take_over_counts": "45",
    "total_take_over_duration": "1429.95765617",
    "total_bag_size": "0",
    "total_fault_counts": "0",
    "total_accident_counts": "0",
    "day": "20190711",
    "create_time": "1583073468"
  },
  {
    "total_id": "201907161583073784964786FKsU",
    "vehicle_id": "arts16_1",
    "park_id": "jiading_innovation_port",
    "total_running_time": "95026",
    "total_running_length": "90805.9678197",
    "total_emergency_stop_counts": "0",
    "total_emergency_stop_duration": "0",
    "total_take_over_counts": "48",
    "total_take_over_duration": "1489.83954993",
    "total_bag_size": "0",
    "total_fault_counts": "0",
    "total_accident_counts": "0",
    "day": "20190716",
    "create_time": "1583073785"
  },
  {
    "total_id": "201907171583073869202039YZcz",
    "vehicle_id": "arts16_1",
    "park_id": "jiading_innovation_port",
    "total_running_time": "102454",
    "total_running_length": "97378.1637852",
    "total_emergency_stop_counts": "0",
    "total_emergency_stop_duration": "0",
    "total_take_over_counts": "53",
    "total_take_over_duration": "1893.78832103",
    "total_bag_size": "0",
    "total_fault_counts": "0",
    "total_accident_counts": "0",
    "day": "20190717",
    "create_time": "1583073869"
  },
  {
    "total_id": "201907181583073944421244Mfvc",
    "vehicle_id": "arts16_1",
    "park_id": "jiading_innovation_port",
    "total_running_time": "108072",
    "total_running_length": "102218.985795",
    "total_emergency_stop_counts": "0",
    "total_emergency_stop_duration": "0",
    "total_take_over_counts": "53",
    "total_take_over_duration": "1893.78832103",
    "total_bag_size": "0",
    "total_fault_counts": "0",
    "total_accident_counts": "0",
    "day": "20190718",
    "create_time": "1583073944"
  },
  {
    "total_id": "201907191583074020296996ohEb",
    "vehicle_id": "arts16_1",
    "park_id": "jiading_innovation_port",
    "total_running_time": "115276",
    "total_running_length": "108393.983635",
    "total_emergency_stop_counts": "0",
    "total_emergency_stop_duration": "0",
    "total_take_over_counts": "58",
    "total_take_over_duration": "1961.85332199",
    "total_bag_size": "0",
    "total_fault_counts": "0",
    "total_accident_counts": "0",
    "day": "20190719",
    "create_time": "1583074020"
  },
  {
    "total_id": "201907201583074092409398Uopn",
    "vehicle_id": "arts16_1",
    "park_id": "jiading_innovation_port",
    "total_running_time": "122865",
    "total_running_length": "114148.084861",
    "total_emergency_stop_counts": "0",
    "total_emergency_stop_duration": "0",
    "total_take_over_counts": "59",
    "total_take_over_duration": "1963.8520168",
    "total_bag_size": "0",
    "total_fault_counts": "0",
    "total_accident_counts": "0",
    "day": "20190720",
    "create_time": "1583074092"
  },
  {
    "total_id": "201907211583074165337970bvrT",
    "vehicle_id": "arts16_1",
    "park_id": "jiading_innovation_port",
    "total_running_time": "131617",
    "total_running_length": "120444.897233",
    "total_emergency_stop_counts": "0",
    "total_emergency_stop_duration": "0",
    "total_take_over_counts": "64",
    "total_take_over_duration": "2126.69465906",
    "total_bag_size": "0",
    "total_fault_counts": "0",
    "total_accident_counts": "0",
    "day": "20190721",
    "create_time": "1583074165"
  },
  {
    "total_id": "201907221583074232179325IKUK",
    "vehicle_id": "arts16_1",
    "park_id": "jiading_innovation_port",
    "total_running_time": "139796",
    "total_running_length": "122556.535725",
    "total_emergency_stop_counts": "0",
    "total_emergency_stop_duration": "0",
    "total_take_over_counts": "68",
    "total_take_over_duration": "2425.47918104",
    "total_bag_size": "0",
    "total_fault_counts": "0",
    "total_accident_counts": "0",
    "day": "20190722",
    "create_time": "1583074232"
  },
  {
    "total_id": "201907241583074382180924fnXS",
    "vehicle_id": "arts16_1",
    "park_id": "jiading_innovation_port",
    "total_running_time": "146426",
    "total_running_length": "128767.844184",
    "total_emergency_stop_counts": "0",
    "total_emergency_stop_duration": "0",
    "total_take_over_counts": "69",
    "total_take_over_duration": "2558.55570849",
    "total_bag_size": "0",
    "total_fault_counts": "0",
    "total_accident_counts": "0",
    "day": "20190724",
    "create_time": "1583074382"
  },
  {
    "total_id": "201907251583074464672012CkDJ",
    "vehicle_id": "arts16_1",
    "park_id": "jiading_innovation_port",
    "total_running_time": "152298",
    "total_running_length": "134290.480636",
    "total_emergency_stop_counts": "0",
    "total_emergency_stop_duration": "0",
    "total_take_over_counts": "72",
    "total_take_over_duration": "2684.34885127",
    "total_bag_size": "0",
    "total_fault_counts": "0",
    "total_accident_counts": "0",
    "day": "20190725",
    "create_time": "1583074465"
  },
  {
    "total_id": "201907261583074549963872hTVp",
    "vehicle_id": "arts16_1",
    "park_id": "jiading_innovation_port",
    "total_running_time": "158671",
    "total_running_length": "139947.431017",
    "total_emergency_stop_counts": "0",
    "total_emergency_stop_duration": "0",
    "total_take_over_counts": "75",
    "total_take_over_duration": "2791.97228182",
    "total_bag_size": "0",
    "total_fault_counts": "0",
    "total_accident_counts": "0",
    "day": "20190726",
    "create_time": "1583074550"
  },
  {
    "total_id": "201907271583074646229153NlnE",
    "vehicle_id": "arts16_1",
    "park_id": "jiading_innovation_port",
    "total_running_time": "164480",
    "total_running_length": "145473.245067",
    "total_emergency_stop_counts": "0",
    "total_emergency_stop_duration": "0",
    "total_take_over_counts": "75",
    "total_take_over_duration": "2791.97228182",
    "total_bag_size": "0",
    "total_fault_counts": "0",
    "total_accident_counts": "0",
    "day": "20190727",
    "create_time": "1583074646"
  },
  {
    "total_id": "201907281583074705031858yFrI",
    "vehicle_id": "arts16_1",
    "park_id": "jiading_innovation_port",
    "total_running_time": "167495",
    "total_running_length": "148400.757173",
    "total_emergency_stop_counts": "0",
    "total_emergency_stop_duration": "0",
    "total_take_over_counts": "76",
    "total_take_over_duration": "2793.97155102",
    "total_bag_size": "0",
    "total_fault_counts": "0",
    "total_accident_counts": "0",
    "day": "20190728",
    "create_time": "1583074705"
  },
  {
    "total_id": "201907291583074789144078exJq",
    "vehicle_id": "arts16_1",
    "park_id": "jiading_innovation_port",
    "total_running_time": "170538",
    "total_running_length": "150939.673261",
    "total_emergency_stop_counts": "0",
    "total_emergency_stop_duration": "0",
    "total_take_over_counts": "76",
    "total_take_over_duration": "2793.97155102",
    "total_bag_size": "0",
    "total_fault_counts": "0",
    "total_accident_counts": "0",
    "day": "20190729",
    "create_time": "1583074789"
  },
  {
    "total_id": "201907301583074887895122KhUX",
    "vehicle_id": "arts16_1",
    "park_id": "jiading_innovation_port",
    "total_running_time": "176253",
    "total_running_length": "156327.743669",
    "total_emergency_stop_counts": "0",
    "total_emergency_stop_duration": "0",
    "total_take_over_counts": "76",
    "total_take_over_duration": "2793.97155102",
    "total_bag_size": "0",
    "total_fault_counts": "0",
    "total_accident_counts": "0",
    "day": "20190730",
    "create_time": "1583074888"
  },
  {
    "total_id": "201907311583074991340332dBgp",
    "vehicle_id": "arts16_1",
    "park_id": "jiading_innovation_port",
    "total_running_time": "185239",
    "total_running_length": "162305.961008",
    "total_emergency_stop_counts": "0",
    "total_emergency_stop_duration": "0",
    "total_take_over_counts": "78",
    "total_take_over_duration": "2829.27051149",
    "total_bag_size": "0",
    "total_fault_counts": "0",
    "total_accident_counts": "0",
    "day": "20190731",
    "create_time": "1583074991"
  },
  {
    "total_id": "201908011583075100973210VKIP",
    "vehicle_id": "arts16_1",
    "park_id": "jiading_innovation_port",
    "total_running_time": "191170",
    "total_running_length": "165103.848947",
    "total_emergency_stop_counts": "0",
    "total_emergency_stop_duration": "0",
    "total_take_over_counts": "78",
    "total_take_over_duration": "2829.27051149",
    "total_bag_size": "0",
    "total_fault_counts": "0",
    "total_accident_counts": "0",
    "day": "20190801",
    "create_time": "1583075101"
  },
  {
    "total_id": "201908021583075178742711ouNL",
    "vehicle_id": "arts16_1",
    "park_id": "jiading_innovation_port",
    "total_running_time": "197307",
    "total_running_length": "168850.86008",
    "total_emergency_stop_counts": "0",
    "total_emergency_stop_duration": "0",
    "total_take_over_counts": "78",
    "total_take_over_duration": "2829.27051149",
    "total_bag_size": "0",
    "total_fault_counts": "0",
    "total_accident_counts": "0",
    "day": "20190802",
    "create_time": "1583075179"
  },
  {
    "total_id": "201908031583075283607498BzFw",
    "vehicle_id": "arts16_1",
    "park_id": "jiading_innovation_port",
    "total_running_time": "204101",
    "total_running_length": "174175.792685",
    "total_emergency_stop_counts": "0",
    "total_emergency_stop_duration": "0",
    "total_take_over_counts": "78",
    "total_take_over_duration": "2829.27051149",
    "total_bag_size": "0",
    "total_fault_counts": "0",
    "total_accident_counts": "0",
    "day": "20190803",
    "create_time": "1583075284"
  },
  {
    "total_id": "201908041583075334130320XJGh",
    "vehicle_id": "arts16_1",
    "park_id": "jiading_innovation_port",
    "total_running_time": "210077",
    "total_running_length": "179649.874043",
    "total_emergency_stop_counts": "0",
    "total_emergency_stop_duration": "0",
    "total_take_over_counts": "78",
    "total_take_over_duration": "2829.27051149",
    "total_bag_size": "0",
    "total_fault_counts": "0",
    "total_accident_counts": "0",
    "day": "20190804",
    "create_time": "1583075334"
  },
  {
    "total_id": "201908051583075436493848YAaZ",
    "vehicle_id": "arts16_1",
    "park_id": "jiading_innovation_port",
    "total_running_time": "215908",
    "total_running_length": "181213.264753",
    "total_emergency_stop_counts": "0",
    "total_emergency_stop_duration": "0",
    "total_take_over_counts": "78",
    "total_take_over_duration": "2829.27051149",
    "total_bag_size": "0",
    "total_fault_counts": "0",
    "total_accident_counts": "0",
    "day": "20190805",
    "create_time": "1583075437"
  },
  {
    "total_id": "201908061583075528502803Zntz",
    "vehicle_id": "arts16_1",
    "park_id": "jiading_innovation_port",
    "total_running_time": "221656",
    "total_running_length": "186451.52078",
    "total_emergency_stop_counts": "0",
    "total_emergency_stop_duration": "0",
    "total_take_over_counts": "78",
    "total_take_over_duration": "2829.27051149",
    "total_bag_size": "0",
    "total_fault_counts": "0",
    "total_accident_counts": "0",
    "day": "20190806",
    "create_time": "1583075529"
  },
  {
    "total_id": "201912091583088006486430TMoO",
    "vehicle_id": "arts16_1",
    "park_id": "shanghai_songjiang_test",
    "total_running_time": "8468",
    "total_running_length": "3544.27179856",
    "total_emergency_stop_counts": "0",
    "total_emergency_stop_duration": "0",
    "total_take_over_counts": "8",
    "total_take_over_duration": "659.875040535",
    "total_bag_size": "0",
    "total_fault_counts": "0",
    "total_accident_counts": "0",
    "day": "20191209",
    "create_time": "1583088007"
  },
  {
    "total_id": "201912101583088115536191CEYP",
    "vehicle_id": "arts16_1",
    "park_id": "shanghai_songjiang_test",
    "total_running_time": "10613",
    "total_running_length": "4004.19955931",
    "total_emergency_stop_counts": "0",
    "total_emergency_stop_duration": "0",
    "total_take_over_counts": "9",
    "total_take_over_duration": "849.440202003",
    "total_bag_size": "0",
    "total_fault_counts": "0",
    "total_accident_counts": "0",
    "day": "20191210",
    "create_time": "1583088116"
  },
  {
    "total_id": "201912111583088251061044OHSD",
    "vehicle_id": "arts16_1",
    "park_id": "shanghai_songjiang_test",
    "total_running_time": "12301",
    "total_running_length": "4846.50015188",
    "total_emergency_stop_counts": "0",
    "total_emergency_stop_duration": "0",
    "total_take_over_counts": "10",
    "total_take_over_duration": "905.269685752",
    "total_bag_size": "0",
    "total_fault_counts": "0",
    "total_accident_counts": "0",
    "day": "20191211",
    "create_time": "1583088251"
  },
  {
    "total_id": "201912121583088398362031AqpC",
    "vehicle_id": "arts16_1",
    "park_id": "shanghai_songjiang_test",
    "total_running_time": "14911",
    "total_running_length": "6099.49458273",
    "total_emergency_stop_counts": "0",
    "total_emergency_stop_duration": "0",
    "total_take_over_counts": "11",
    "total_take_over_duration": "919.239520794",
    "total_bag_size": "0",
    "total_fault_counts": "0",
    "total_accident_counts": "0",
    "day": "20191212",
    "create_time": "1583088398"
  },
  {
    "total_id": "201912131583088534262317oNoy",
    "vehicle_id": "arts16_1",
    "park_id": "shanghai_songjiang_test",
    "total_running_time": "18205",
    "total_running_length": "7839.53339917",
    "total_emergency_stop_counts": "0",
    "total_emergency_stop_duration": "0",
    "total_take_over_counts": "14",
    "total_take_over_duration": "962.508946662",
    "total_bag_size": "0",
    "total_fault_counts": "0",
    "total_accident_counts": "0",
    "day": "20191213",
    "create_time": "1583088534"
  },
  {
    "total_id": "201912161583088831533229ARaX",
    "vehicle_id": "arts16_1",
    "park_id": "shanghai_songjiang_test",
    "total_running_time": "22581",
    "total_running_length": "9893.52321944",
    "total_emergency_stop_counts": "0",
    "total_emergency_stop_duration": "0",
    "total_take_over_counts": "14",
    "total_take_over_duration": "962.508946662",
    "total_bag_size": "0",
    "total_fault_counts": "0",
    "total_accident_counts": "0",
    "day": "20191216",
    "create_time": "1583088832"
  },
  {
    "total_id": "201912171583088945014541TXFF",
    "vehicle_id": "arts16_1",
    "park_id": "shanghai_songjiang_test",
    "total_running_time": "26583",
    "total_running_length": "11791.255904",
    "total_emergency_stop_counts": "4",
    "total_emergency_stop_duration": "23.969723702",
    "total_take_over_counts": "16",
    "total_take_over_duration": "1085.41812826",
    "total_bag_size": "0",
    "total_fault_counts": "0",
    "total_accident_counts": "0",
    "day": "20191217",
    "create_time": "1583088945"
  },
  {
    "total_id": "201912181583089065091237Ybuz",
    "vehicle_id": "arts16_1",
    "park_id": "shanghai_songjiang_test",
    "total_running_time": "29642",
    "total_running_length": "13350.6707884",
    "total_emergency_stop_counts": "4",
    "total_emergency_stop_duration": "23.969723702",
    "total_take_over_counts": "18",
    "total_take_over_duration": "1101.3980415",
    "total_bag_size": "0",
    "total_fault_counts": "0",
    "total_accident_counts": "0",
    "day": "20191218",
    "create_time": "1583089065"
  },
  {
    "total_id": "201912201583089318175907QGVj",
    "vehicle_id": "arts16_1",
    "park_id": "shanghai_songjiang_test",
    "total_running_time": "34351",
    "total_running_length": "15403.3257832",
    "total_emergency_stop_counts": "4",
    "total_emergency_stop_duration": "23.969723702",
    "total_take_over_counts": "21",
    "total_take_over_duration": "1131.16730477",
    "total_bag_size": "0",
    "total_fault_counts": "0",
    "total_accident_counts": "0",
    "day": "20191220",
    "create_time": "1583089318"
  },
  {
    "total_id": "201912231583089659211754TIrn",
    "vehicle_id": "arts16_1",
    "park_id": "shanghai_songjiang_test",
    "total_running_time": "36828",
    "total_running_length": "16663.7400461",
    "total_emergency_stop_counts": "4",
    "total_emergency_stop_duration": "23.969723702",
    "total_take_over_counts": "23",
    "total_take_over_duration": "1144.98651411",
    "total_bag_size": "0",
    "total_fault_counts": "0",
    "total_accident_counts": "0",
    "day": "20191223",
    "create_time": "1583089659"
  },
  {
    "total_id": "201912241583089797462700FgzX",
    "vehicle_id": "arts16_1",
    "park_id": "shanghai_songjiang_test",
    "total_running_time": "46400",
    "total_running_length": "21335.4544395",
    "total_emergency_stop_counts": "7",
    "total_emergency_stop_duration": "75.966501712",
    "total_take_over_counts": "30",
    "total_take_over_duration": "1483.76442339",
    "total_bag_size": "0",
    "total_fault_counts": "0",
    "total_accident_counts": "0",
    "day": "20191224",
    "create_time": "1583089798"
  },
  {
    "total_id": "201912251583089932735145iNHP",
    "vehicle_id": "arts16_1",
    "park_id": "shanghai_songjiang_test",
    "total_running_time": "49991",
    "total_running_length": "22911.5655696",
    "total_emergency_stop_counts": "7",
    "total_emergency_stop_duration": "75.966501712",
    "total_take_over_counts": "31",
    "total_take_over_duration": "1485.77446272",
    "total_bag_size": "0",
    "total_fault_counts": "0",
    "total_accident_counts": "0",
    "day": "20191225",
    "create_time": "1583089933"
  },
  {
    "total_id": "201912261583090062429814ijwz",
    "vehicle_id": "arts16_1",
    "park_id": "shanghai_songjiang_test",
    "total_running_time": "53500",
    "total_running_length": "24138.8814873",
    "total_emergency_stop_counts": "7",
    "total_emergency_stop_duration": "75.966501712",
    "total_take_over_counts": "33",
    "total_take_over_duration": "1493.78420832",
    "total_bag_size": "0",
    "total_fault_counts": "0",
    "total_accident_counts": "0",
    "day": "20191226",
    "create_time": "1583090062"
  },
  {
    "total_id": "202001081583091572550206cmle",
    "vehicle_id": "arts16_1",
    "park_id": "suzhou_xiangcheng_demo",
    "total_running_time": "3814",
    "total_running_length": "440.6978369",
    "total_emergency_stop_counts": "6",
    "total_emergency_stop_duration": "65.881309748",
    "total_take_over_counts": "2",
    "total_take_over_duration": "410.02231359",
    "total_bag_size": "0",
    "total_fault_counts": "0",
    "total_accident_counts": "0",
    "day": "20200108",
    "create_time": "1583091573"
  },
  {
    "total_id": "202001141583092341169677gAwd",
    "vehicle_id": "arts16_1",
    "park_id": "suzhou_xiangcheng_demo",
    "total_running_time": "12851",
    "total_running_length": "4885.98217108",
    "total_emergency_stop_counts": "41",
    "total_emergency_stop_duration": "2774.95132804",
    "total_take_over_counts": "22",
    "total_take_over_duration": "3210.25527",
    "total_bag_size": "0",
    "total_fault_counts": "0",
    "total_accident_counts": "0",
    "day": "20200114",
    "create_time": "1583092341"
  },
  {
    "total_id": "202001151583092498211639lwjt",
    "vehicle_id": "arts16_1",
    "park_id": "suzhou_xiangcheng_demo",
    "total_running_time": "26907",
    "total_running_length": "12260.1773639",
    "total_emergency_stop_counts": "67",
    "total_emergency_stop_duration": "4862.27008725",
    "total_take_over_counts": "48",
    "total_take_over_duration": "5669.61661887",
    "total_bag_size": "0",
    "total_fault_counts": "0",
    "total_accident_counts": "0",
    "day": "20200115",
    "create_time": "1583092498"
  },
  {
    "total_id": "202001171583092730895888fYnj",
    "vehicle_id": "arts16_1",
    "park_id": "suzhou_xiangcheng_demo",
    "total_running_time": "34691",
    "total_running_length": "18410.2018697",
    "total_emergency_stop_counts": "85",
    "total_emergency_stop_duration": "5845.41804744",
    "total_take_over_counts": "60",
    "total_take_over_duration": "6379.67953968",
    "total_bag_size": "0",
    "total_fault_counts": "0",
    "total_accident_counts": "0",
    "day": "20200117",
    "create_time": "1583092731"
  },
  {
    "total_id": "202001191583092937847006YqXA",
    "vehicle_id": "arts16_1",
    "park_id": "suzhou_xiangcheng_demo",
    "total_running_time": "44735",
    "total_running_length": "25866.3914878",
    "total_emergency_stop_counts": "148",
    "total_emergency_stop_duration": "8855.25570965",
    "total_take_over_counts": "77",
    "total_take_over_duration": "7994.84227919",
    "total_bag_size": "0",
    "total_fault_counts": "0",
    "total_accident_counts": "0",
    "day": "20200119",
    "create_time": "1583092938"
  },
  {
    "total_id": "202001201583093066127561aPKa",
    "vehicle_id": "arts16_1",
    "park_id": "suzhou_xiangcheng_demo",
    "total_running_time": "55709",
    "total_running_length": "36468.4539443",
    "total_emergency_stop_counts": "180",
    "total_emergency_stop_duration": "9609.65145016",
    "total_take_over_counts": "86",
    "total_take_over_duration": "8654.9102981",
    "total_bag_size": "0",
    "total_fault_counts": "0",
    "total_accident_counts": "0",
    "day": "20200120",
    "create_time": "1583093066"
  },
  {
    "total_id": "202001211583093175220411tpPr",
    "vehicle_id": "arts16_1",
    "park_id": "suzhou_xiangcheng_demo",
    "total_running_time": "61774",
    "total_running_length": "42667.1369096",
    "total_emergency_stop_counts": "196",
    "total_emergency_stop_duration": "9729.98910737",
    "total_take_over_counts": "94",
    "total_take_over_duration": "9009.88368343",
    "total_bag_size": "0",
    "total_fault_counts": "0",
    "total_accident_counts": "0",
    "day": "20200121",
    "create_time": "1583093175"
  },
  {
    "total_id": "202001231583093347239252ICZk",
    "vehicle_id": "arts16_1",
    "park_id": "suzhou_xiangcheng_demo",
    "total_running_time": "64661",
    "total_running_length": "45815.5101552",
    "total_emergency_stop_counts": "200",
    "total_emergency_stop_duration": "9754.0486865",
    "total_take_over_counts": "95",
    "total_take_over_duration": "9045.96317362",
    "total_bag_size": "0",
    "total_fault_counts": "0",
    "total_accident_counts": "0",
    "day": "20200123",
    "create_time": "1583093347"
  },
  {
    "total_id": "202001271583093630445590UABT",
    "vehicle_id": "arts16_1",
    "park_id": "suzhou_xiangcheng_demo",
    "total_running_time": "70016",
    "total_running_length": "51246.0416555",
    "total_emergency_stop_counts": "213",
    "total_emergency_stop_duration": "10026.9674458",
    "total_take_over_counts": "100",
    "total_take_over_duration": "9355.41243409",
    "total_bag_size": "0",
    "total_fault_counts": "0",
    "total_accident_counts": "0",
    "day": "20200127",
    "create_time": "1583093630"
  },
  {
    "total_id": "202002101583094353255095SfLJ",
    "vehicle_id": "arts16_1",
    "park_id": "suzhou_xiangcheng_demo",
    "total_running_time": "79364",
    "total_running_length": "61671.538922",
    "total_emergency_stop_counts": "225",
    "total_emergency_stop_duration": "10145.3089792",
    "total_take_over_counts": "103",
    "total_take_over_duration": "9535.85271739",
    "total_bag_size": "0",
    "total_fault_counts": "0",
    "total_accident_counts": "0",
    "day": "20200210",
    "create_time": "1583094353"
  },
  {
    "total_id": "202002121583094503836560aexA",
    "vehicle_id": "arts16_1",
    "park_id": "suzhou_xiangcheng_demo",
    "total_running_time": "87595",
    "total_running_length": "70364.2814714",
    "total_emergency_stop_counts": "255",
    "total_emergency_stop_duration": "10979.7899992",
    "total_take_over_counts": "125",
    "total_take_over_duration": "10394.2322464",
    "total_bag_size": "0",
    "total_fault_counts": "0",
    "total_accident_counts": "0",
    "day": "20200212",
    "create_time": "1583094504"
  },
  {
    "total_id": "202002131583094607397540smQf",
    "vehicle_id": "arts16_1",
    "park_id": "suzhou_xiangcheng_demo",
    "total_running_time": "96556",
    "total_running_length": "80717.9779004",
    "total_emergency_stop_counts": "270",
    "total_emergency_stop_duration": "11505.2585942",
    "total_take_over_counts": "131",
    "total_take_over_duration": "10571.2064323",
    "total_bag_size": "0",
    "total_fault_counts": "0",
    "total_accident_counts": "0",
    "day": "20200213",
    "create_time": "1583094607"
  },
  {
    "total_id": "202002141583094688233072XOqs",
    "vehicle_id": "arts16_1",
    "park_id": "suzhou_xiangcheng_demo",
    "total_running_time": "106692",
    "total_running_length": "90083.5634829",
    "total_emergency_stop_counts": "280",
    "total_emergency_stop_duration": "12222.5733804",
    "total_take_over_counts": "137",
    "total_take_over_duration": "10852.0869989",
    "total_bag_size": "0",
    "total_fault_counts": "0",
    "total_accident_counts": "0",
    "day": "20200214",
    "create_time": "1583094688"
  },
  {
    "total_id": "202002151583094756703796ojxJ",
    "vehicle_id": "arts16_1",
    "park_id": "suzhou_xiangcheng_demo",
    "total_running_time": "113934",
    "total_running_length": "95827.9860767",
    "total_emergency_stop_counts": "290",
    "total_emergency_stop_duration": "12393.089647",
    "total_take_over_counts": "143",
    "total_take_over_duration": "11044.6502063",
    "total_bag_size": "0",
    "total_fault_counts": "0",
    "total_accident_counts": "0",
    "day": "20200215",
    "create_time": "1583094757"
  },
  {
    "total_id": "202002161583094827894373cbAx",
    "vehicle_id": "arts16_1",
    "park_id": "suzhou_xiangcheng_demo",
    "total_running_time": "116102",
    "total_running_length": "97919.6632573",
    "total_emergency_stop_counts": "292",
    "total_emergency_stop_duration": "12399.1137556",
    "total_take_over_counts": "144",
    "total_take_over_duration": "11088.7698064",
    "total_bag_size": "0",
    "total_fault_counts": "0",
    "total_accident_counts": "0",
    "day": "20200216",
    "create_time": "1583094828"
  },
  {
    "total_id": "202002181583094988587212DSwo",
    "vehicle_id": "arts16_1",
    "park_id": "suzhou_xiangcheng_demo",
    "total_running_time": "122684",
    "total_running_length": "104187.509674",
    "total_emergency_stop_counts": "302",
    "total_emergency_stop_duration": "12828.2301313",
    "total_take_over_counts": "145",
    "total_take_over_duration": "11367.499959",
    "total_bag_size": "0",
    "total_fault_counts": "0",
    "total_accident_counts": "0",
    "day": "20200218",
    "create_time": "1583094989"
  },
  {
    "total_id": "202002191583095086818710jsGc",
    "vehicle_id": "arts16_1",
    "park_id": "suzhou_xiangcheng_demo",
    "total_running_time": "132799",
    "total_running_length": "114136.757044",
    "total_emergency_stop_counts": "317",
    "total_emergency_stop_duration": "13219.402259",
    "total_take_over_counts": "153",
    "total_take_over_duration": "11651.3610706",
    "total_bag_size": "0",
    "total_fault_counts": "0",
    "total_accident_counts": "0",
    "day": "20200219",
    "create_time": "1583095087"
  },
  {
    "total_id": "202002201583110699267320evbP",
    "vehicle_id": "arts16_1",
    "park_id": "suzhou_xiangcheng_demo",
    "total_running_time": "142813",
    "total_running_length": "124537.829332",
    "total_emergency_stop_counts": "329",
    "total_emergency_stop_duration": "13374.4782306",
    "total_take_over_counts": "159",
    "total_take_over_duration": "11902.0833954",
    "total_bag_size": "0",
    "total_fault_counts": "0",
    "total_accident_counts": "0",
    "day": "20200220",
    "create_time": "1583110699"
  },
  {
    "total_id": "202002211583110727012854BtKG",
    "vehicle_id": "arts16_1",
    "park_id": "suzhou_xiangcheng_demo",
    "total_running_time": "152294",
    "total_running_length": "134907.217278",
    "total_emergency_stop_counts": "342",
    "total_emergency_stop_duration": "14032.2861158",
    "total_take_over_counts": "167",
    "total_take_over_duration": "12668.0995473",
    "total_bag_size": "0",
    "total_fault_counts": "0",
    "total_accident_counts": "0",
    "day": "20200221",
    "create_time": "1583110727"
  },
  {
    "total_id": "202002221583110753655959OmyC",
    "vehicle_id": "arts16_1",
    "park_id": "suzhou_xiangcheng_demo",
    "total_running_time": "162581",
    "total_running_length": "145301.856354",
    "total_emergency_stop_counts": "358",
    "total_emergency_stop_duration": "14193.5362743",
    "total_take_over_counts": "175",
    "total_take_over_duration": "12862.6873771",
    "total_bag_size": "0",
    "total_fault_counts": "0",
    "total_accident_counts": "0",
    "day": "20200222",
    "create_time": "1583110754"
  },
  {
    "total_id": "202002231583110777911407rcvj",
    "vehicle_id": "arts16_1",
    "park_id": "suzhou_xiangcheng_demo",
    "total_running_time": "172486",
    "total_running_length": "155684.816423",
    "total_emergency_stop_counts": "364",
    "total_emergency_stop_duration": "14205.5737098",
    "total_take_over_counts": "180",
    "total_take_over_duration": "12979.0262896",
    "total_bag_size": "0",
    "total_fault_counts": "0",
    "total_accident_counts": "0",
    "day": "20200223",
    "create_time": "1583110778"
  },
  {
    "total_id": "202002241583110807010929QvXs",
    "vehicle_id": "arts16_1",
    "park_id": "suzhou_xiangcheng_demo",
    "total_running_time": "183829",
    "total_running_length": "166042.364868",
    "total_emergency_stop_counts": "379",
    "total_emergency_stop_duration": "15835.1328364",
    "total_take_over_counts": "189",
    "total_take_over_duration": "13643.7073664",
    "total_bag_size": "0",
    "total_fault_counts": "0",
    "total_accident_counts": "0",
    "day": "20200224",
    "create_time": "1583110807"
  },
  {
    "total_id": "202002251583110836623399wGMJ",
    "vehicle_id": "arts16_1",
    "park_id": "suzhou_xiangcheng_demo",
    "total_running_time": "193942",
    "total_running_length": "176412.373153",
    "total_emergency_stop_counts": "392",
    "total_emergency_stop_duration": "16241.390807",
    "total_take_over_counts": "192",
    "total_take_over_duration": "13735.9894938",
    "total_bag_size": "0",
    "total_fault_counts": "0",
    "total_accident_counts": "0",
    "day": "20200225",
    "create_time": "1583110837"
  },
  {
    "total_id": "202002261583110864842925uYgL",
    "vehicle_id": "arts16_1",
    "park_id": "suzhou_xiangcheng_demo",
    "total_running_time": "199801",
    "total_running_length": "180332.789615",
    "total_emergency_stop_counts": "395",
    "total_emergency_stop_duration": "16291.5114745",
    "total_take_over_counts": "192",
    "total_take_over_duration": "13735.9894938",
    "total_bag_size": "0",
    "total_fault_counts": "0",
    "total_accident_counts": "0",
    "day": "20200226",
    "create_time": "1583110865"
  },
  {
    "total_id": "202002271583110893825251fLsH",
    "vehicle_id": "arts16_1",
    "park_id": "suzhou_xiangcheng_demo",
    "total_running_time": "206711",
    "total_running_length": "187027.94697",
    "total_emergency_stop_counts": "404",
    "total_emergency_stop_duration": "16371.7218427",
    "total_take_over_counts": "203",
    "total_take_over_duration": "14014.8001451",
    "total_bag_size": "0",
    "total_fault_counts": "0",
    "total_accident_counts": "0",
    "day": "20200227",
    "create_time": "1583110894"
  },
  {
    "total_id": "202002281583110922580801ZWku",
    "vehicle_id": "arts16_1",
    "park_id": "suzhou_xiangcheng_demo",
    "total_running_time": "210344",
    "total_running_length": "189954.739913",
    "total_emergency_stop_counts": "412",
    "total_emergency_stop_duration": "16644.5857059",
    "total_take_over_counts": "205",
    "total_take_over_duration": "14054.9174511",
    "total_bag_size": "0",
    "total_fault_counts": "0",
    "total_accident_counts": "0",
    "day": "20200228",
    "create_time": "1583110923"
  },
  {
    "total_id": "202002291583110951528153AehF",
    "vehicle_id": "arts16_1",
    "park_id": "suzhou_xiangcheng_demo",
    "total_running_time": "222549",
    "total_running_length": "199895.123481",
    "total_emergency_stop_counts": "436",
    "total_emergency_stop_duration": "18162.7737895",
    "total_take_over_counts": "212",
    "total_take_over_duration": "14203.2698352",
    "total_bag_size": "0",
    "total_fault_counts": "0",
    "total_accident_counts": "0",
    "day": "20200229",
    "create_time": "1583110952"
  },
  {
    "total_id": "202003011583110980546608kbpB",
    "vehicle_id": "arts16_1",
    "park_id": "suzhou_xiangcheng_demo",
    "total_running_time": "232347",
    "total_running_length": "210210.78332",
    "total_emergency_stop_counts": "467",
    "total_emergency_stop_duration": "19043.2652563",
    "total_take_over_counts": "222",
    "total_take_over_duration": "14405.8305363",
    "total_bag_size": "0",
    "total_fault_counts": "0",
    "total_accident_counts": "0",
    "day": "20200301",
    "create_time": "1583110981"
  },
  {
    "total_id": "202003021583456260105809ntaV",
    "vehicle_id": "arts16_1",
    "park_id": "suzhou_xiangcheng_demo",
    "total_running_time": "243098",
    "total_running_length": "220267.386706",
    "total_emergency_stop_counts": "491",
    "total_emergency_stop_duration": "19986.5437211",
    "total_take_over_counts": "227",
    "total_take_over_duration": "14620.5797321",
    "total_bag_size": "0",
    "total_fault_counts": "0",
    "total_accident_counts": "0",
    "day": "20200302",
    "create_time": "1583456260"
  },
  {
    "total_id": "202003031583456289190722Aaqu",
    "vehicle_id": "arts16_1",
    "park_id": "suzhou_xiangcheng_demo",
    "total_running_time": "253239",
    "total_running_length": "230325.114445",
    "total_emergency_stop_counts": "511",
    "total_emergency_stop_duration": "20530.1326786",
    "total_take_over_counts": "231",
    "total_take_over_duration": "14751.0011453",
    "total_bag_size": "0",
    "total_fault_counts": "0",
    "total_accident_counts": "0",
    "day": "20200303",
    "create_time": "1583456289"
  },
  {
    "total_id": "202003041583456317106201kldq",
    "vehicle_id": "arts16_1",
    "park_id": "suzhou_xiangcheng_demo",
    "total_running_time": "256993",
    "total_running_length": "234446.985245",
    "total_emergency_stop_counts": "526",
    "total_emergency_stop_duration": "20895.2391158",
    "total_take_over_counts": "232",
    "total_take_over_duration": "14765.0511143",
    "total_bag_size": "0",
    "total_fault_counts": "0",
    "total_accident_counts": "0",
    "day": "20200304",
    "create_time": "1583456317"
  },
  {
    "total_id": "202003051583456345371200GhZj",
    "vehicle_id": "arts16_1",
    "park_id": "suzhou_xiangcheng_demo",
    "total_running_time": "261326",
    "total_running_length": "238568.486328",
    "total_emergency_stop_counts": "545",
    "total_emergency_stop_duration": "21623.4421845",
    "total_take_over_counts": "235",
    "total_take_over_duration": "14881.4096296",
    "total_bag_size": "0",
    "total_fault_counts": "0",
    "total_accident_counts": "0",
    "day": "20200305",
    "create_time": "1583456345"
  },
  {
    "total_id": "202003071583809689143565tpnd",
    "vehicle_id": "arts16_1",
    "park_id": "suzhou_xiangcheng_demo",
    "total_running_time": "271404",
    "total_running_length": "248828.791978",
    "total_emergency_stop_counts": "566",
    "total_emergency_stop_duration": "23400.364357",
    "total_take_over_counts": "243",
    "total_take_over_duration": "15066.0308552",
    "total_bag_size": "0",
    "total_fault_counts": "0",
    "total_accident_counts": "0",
    "day": "20200307",
    "create_time": "1583809689"
  },
  {
    "total_id": "202003081583809717514079UsrX",
    "vehicle_id": "arts16_1",
    "park_id": "suzhou_xiangcheng_demo",
    "total_running_time": "280576",
    "total_running_length": "257033.953045",
    "total_emergency_stop_counts": "578",
    "total_emergency_stop_duration": "24058.1439536",
    "total_take_over_counts": "250",
    "total_take_over_duration": "15300.7502089",
    "total_bag_size": "0",
    "total_fault_counts": "0",
    "total_accident_counts": "0",
    "day": "20200308",
    "create_time": "1583809718"
  },
  {
    "total_id": "202003091584337322895257CVYP",
    "vehicle_id": "arts16_1",
    "park_id": "suzhou_xiangcheng_demo",
    "total_running_time": "285331",
    "total_running_length": "261328.09679",
    "total_emergency_stop_counts": "581",
    "total_emergency_stop_duration": "24114.3229549",
    "total_take_over_counts": "251",
    "total_take_over_duration": "15324.8000777",
    "total_bag_size": "0",
    "total_fault_counts": "0",
    "total_accident_counts": "0",
    "day": "20200309",
    "create_time": "1584337323"
  },
  {
    "total_id": "202003101584337363219543RLJq",
    "vehicle_id": "arts16_1",
    "park_id": "suzhou_xiangcheng_demo",
    "total_running_time": "289293",
    "total_running_length": "265541.849675",
    "total_emergency_stop_counts": "590",
    "total_emergency_stop_duration": "24336.9455464",
    "total_take_over_counts": "251",
    "total_take_over_duration": "15324.8000777",
    "total_bag_size": "0",
    "total_fault_counts": "0",
    "total_accident_counts": "0",
    "day": "20200310",
    "create_time": "1584337363"
  },
  {
    "total_id": "202003121584337429170511bRui",
    "vehicle_id": "arts16_1",
    "park_id": "suzhou_xiangcheng_demo",
    "total_running_time": "293325",
    "total_running_length": "269767.390012",
    "total_emergency_stop_counts": "590",
    "total_emergency_stop_duration": "24336.9455464",
    "total_take_over_counts": "251",
    "total_take_over_duration": "15324.8000777",
    "total_bag_size": "0",
    "total_fault_counts": "0",
    "total_accident_counts": "0",
    "day": "20200312",
    "create_time": "1584337429"
  },
  {
    "total_id": "202003131584337470283046IpGR",
    "vehicle_id": "arts16_1",
    "park_id": "suzhou_xiangcheng_demo",
    "total_running_time": "302072",
    "total_running_length": "278382.565966",
    "total_emergency_stop_counts": "602",
    "total_emergency_stop_duration": "24929.5903123",
    "total_take_over_counts": "258",
    "total_take_over_duration": "15606.5664897",
    "total_bag_size": "0",
    "total_fault_counts": "0",
    "total_accident_counts": "0",
    "day": "20200313",
    "create_time": "1584337470"
  },
  {
    "total_id": "202003141584337508582012veWn",
    "vehicle_id": "arts16_1",
    "park_id": "suzhou_xiangcheng_demo",
    "total_running_time": "310594",
    "total_running_length": "286827.547585",
    "total_emergency_stop_counts": "612",
    "total_emergency_stop_duration": "25226.4630497",
    "total_take_over_counts": "260",
    "total_take_over_duration": "15660.7064483",
    "total_bag_size": "0",
    "total_fault_counts": "0",
    "total_accident_counts": "0",
    "day": "20200314",
    "create_time": "1584337509"
  },
  {
    "total_id": "202003151584337545160221qOiQ",
    "vehicle_id": "arts16_1",
    "park_id": "suzhou_xiangcheng_demo",
    "total_running_time": "320681",
    "total_running_length": "295247.835434",
    "total_emergency_stop_counts": "625",
    "total_emergency_stop_duration": "25888.2130943",
    "total_take_over_counts": "263",
    "total_take_over_duration": "15748.8963444",
    "total_bag_size": "0",
    "total_fault_counts": "0",
    "total_accident_counts": "0",
    "day": "20200315",
    "create_time": "1584337545"
  },
  {
    "total_id": "202003161584397134994474AzEU",
    "vehicle_id": "arts16_1",
    "park_id": "suzhou_xiangcheng_demo",
    "total_running_time": "328642",
    "total_running_length": "302112.790095",
    "total_emergency_stop_counts": "632",
    "total_emergency_stop_duration": "26030.574704",
    "total_take_over_counts": "268",
    "total_take_over_duration": "15915.3627779",
    "total_bag_size": "0",
    "total_fault_counts": "0",
    "total_accident_counts": "0",
    "day": "20200316",
    "create_time": "1584397135"
  },
  {
    "total_id": "202003171584479695602519AaQw",
    "vehicle_id": "arts16_1",
    "park_id": "suzhou_xiangcheng_demo",
    "total_running_time": "337306",
    "total_running_length": "310532.831343",
    "total_emergency_stop_counts": "641",
    "total_emergency_stop_duration": "26534.0773559",
    "total_take_over_counts": "269",
    "total_take_over_duration": "15999.6228544",
    "total_bag_size": "0",
    "total_fault_counts": "0",
    "total_accident_counts": "0",
    "day": "20200317",
    "create_time": "1584479696"
  },
  {
    "total_id": "202003181584580970752734qWaq",
    "vehicle_id": "arts16_1",
    "park_id": "suzhou_xiangcheng_demo",
    "total_running_time": "340565",
    "total_running_length": "314094.838183",
    "total_emergency_stop_counts": "647",
    "total_emergency_stop_duration": "26714.6152423",
    "total_take_over_counts": "269",
    "total_take_over_duration": "15999.6228544",
    "total_bag_size": "0",
    "total_fault_counts": "0",
    "total_accident_counts": "0",
    "day": "20200318",
    "create_time": "1584580971"
  },
  {
    "total_id": "202003191584666822773656BqYp",
    "vehicle_id": "arts16_1",
    "park_id": "suzhou_xiangcheng_demo",
    "total_running_time": "351604",
    "total_running_length": "324222.9557",
    "total_emergency_stop_counts": "666",
    "total_emergency_stop_duration": "27713.4578515",
    "total_take_over_counts": "277",
    "total_take_over_duration": "16506.9700214",
    "total_bag_size": "0",
    "total_fault_counts": "0",
    "total_accident_counts": "0",
    "day": "20200319",
    "create_time": "1584666823"
  },
  {
    "total_id": "202003201584761436543741dJjS",
    "vehicle_id": "arts16_1",
    "park_id": "suzhou_xiangcheng_demo",
    "total_running_time": "362182",
    "total_running_length": "335182.682173",
    "total_emergency_stop_counts": "678",
    "total_emergency_stop_duration": "28295.5547543",
    "total_take_over_counts": "282",
    "total_take_over_duration": "17026.004233",
    "total_bag_size": "0",
    "total_fault_counts": "0",
    "total_accident_counts": "0",
    "day": "20200320",
    "create_time": "1584761437"
  },
  {
    "total_id": "202003211584837240353004mQNn",
    "vehicle_id": "arts16_1",
    "park_id": "suzhou_xiangcheng_demo",
    "total_running_time": "368410",
    "total_running_length": "341682.085717",
    "total_emergency_stop_counts": "680",
    "total_emergency_stop_duration": "28361.7859693",
    "total_take_over_counts": "283",
    "total_take_over_duration": "17216.3634084",
    "total_bag_size": "0",
    "total_fault_counts": "0",
    "total_accident_counts": "0",
    "day": "20200321",
    "create_time": "1584837240"
  },
  {
    "total_id": "202003221584925586269658yXXj",
    "vehicle_id": "arts16_1",
    "park_id": "suzhou_xiangcheng_demo",
    "total_running_time": "379077",
    "total_running_length": "352830.724144",
    "total_emergency_stop_counts": "693",
    "total_emergency_stop_duration": "29027.677758",
    "total_take_over_counts": "288",
    "total_take_over_duration": "17453.98277",
    "total_bag_size": "0",
    "total_fault_counts": "0",
    "total_accident_counts": "0",
    "day": "20200322",
    "create_time": "1584925586"
  },
  {
    "total_id": "202003231584960175525125gZGj",
    "vehicle_id": "arts16_1",
    "park_id": "suzhou_xiangcheng_demo",
    "total_running_time": "386022",
    "total_running_length": "359588.026839",
    "total_emergency_stop_counts": "701",
    "total_emergency_stop_duration": "29218.3283894",
    "total_take_over_counts": "291",
    "total_take_over_duration": "17779.0674472",
    "total_bag_size": "0",
    "total_fault_counts": "0",
    "total_accident_counts": "0",
    "day": "20200323",
    "create_time": "1584960176"
  },
  {
    "total_id": "202003241585098239198574rgoH",
    "vehicle_id": "arts16_1",
    "park_id": "suzhou_xiangcheng_demo",
    "total_running_time": "395555",
    "total_running_length": "369998.708787",
    "total_emergency_stop_counts": "711",
    "total_emergency_stop_duration": "29485.1033027",
    "total_take_over_counts": "295",
    "total_take_over_duration": "17881.3516979",
    "total_bag_size": "0",
    "total_fault_counts": "0",
    "total_accident_counts": "0",
    "day": "20200324",
    "create_time": "1585098239"
  },
  {
    "total_id": "202003251585185595046670zrtU",
    "vehicle_id": "arts16_1",
    "park_id": "suzhou_xiangcheng_demo",
    "total_running_time": "404438",
    "total_running_length": "378734.667362",
    "total_emergency_stop_counts": "729",
    "total_emergency_stop_duration": "30078.7622094",
    "total_take_over_counts": "297",
    "total_take_over_duration": "17967.5880682",
    "total_bag_size": "0",
    "total_fault_counts": "0",
    "total_accident_counts": "0",
    "day": "20200325",
    "create_time": "1585185595"
  },
  {
    "total_id": "202003261585271178021074cZHD",
    "vehicle_id": "arts16_1",
    "park_id": "suzhou_xiangcheng_demo",
    "total_running_time": "409262",
    "total_running_length": "383740.379041",
    "total_emergency_stop_counts": "733",
    "total_emergency_stop_duration": "30130.9191108",
    "total_take_over_counts": "300",
    "total_take_over_duration": "18067.8316195",
    "total_bag_size": "0",
    "total_fault_counts": "0",
    "total_accident_counts": "0",
    "day": "20200326",
    "create_time": "1585271178"
  }
]
